panlex.py
panlex_API-1.2.0.dist-info/METADATA
panlex_API-1.2.0.dist-info/RECORD
panlex_API-1.2.0.dist-info/WHEEL
panlex_API-1.2.0.dist-info/top_level.txt
