Metadata-Version: 2.1
Name: panlex-API
Version: 1.2.0
Summary: Python wrapper for PanLex API
Home-page: https://github.com/longnow/panlex_python_API
Author: Maxwell Joslyn; Caroline Glazer; Gary Krug; Alex DelPriore; Ben Yang
Author-email: info@panlex.org
License: UNKNOWN
Platform: UNKNOWN
Classifier: Development Status :: 5 - Production/Stable
Classifier: Programming Language :: Python
Classifier: Programming Language :: Python :: 3
Classifier: Operating System :: OS Independent
Classifier: License :: OSI Approved :: MIT License
Classifier: Topic :: Software Development :: Libraries :: Python Modules
Requires-Dist: ratelimit
Requires-Dist: requests
